Metadata-Version: 2.1
Name: autofig
Version: 1.2.0
Summary: High-Level Interface to Create Figures/Animations with Matplotlib
Home-page: https://www.github.com/kecnry/autofig
Author: Kyle Conroy
Author-email: kyleconroy@gmail.com
License: UNKNOWN
Download-URL: https://github.com/kecnry/autofig/tarball/1.1.0
Platform: UNKNOWN
Classifier: Development Status :: 5 - Production/Stable
Classifier: Intended Audience :: Science/Research
Classifier: License :: OSI Approved :: GNU General Public License v3 (GPLv3)
Classifier: Natural Language :: English
Classifier: Operating System :: OS Independent
Classifier: Programming Language :: Python :: 2.7
Classifier: Programming Language :: Python :: 3.6
Classifier: Topic :: Scientific/Engineering
Classifier: Topic :: Software Development :: Libraries :: Python Modules
